MANIFEST.in
README.txt
bootstrap.py
buildout.cfg
setup.cfg
setup.py
appeus/__init__.py
appeus.content.egg-info/PKG-INFO
appeus.content.egg-info/SOURCES.txt
appeus.content.egg-info/dependency_links.txt
appeus.content.egg-info/entry_points.txt
appeus.content.egg-info/namespace_packages.txt
appeus.content.egg-info/not-zip-safe
appeus.content.egg-info/requires.txt
appeus.content.egg-info/top_level.txt
appeus/content/INTEGRATION.txt
appeus/content/__init__.py
appeus/content/app.py
appeus/content/configure.zcml
appeus/content/indexers.py
appeus/content/permissions.zcml
appeus/content/rebuild_i18n.sh
appeus/content/tests.py
appeus/content/vocabularies.py
appeus/content/browser/__init__.py
appeus/content/browser/configure.zcml
appeus/content/locales/README.txt
appeus/content/locales/appeus.content-manual.pot
appeus/content/locales/appeus.content.pot
appeus/content/locales/manual.pot
appeus/content/locales/plone.pot
appeus/content/locales/eu/LC_MESSAGES/appeus.content.po
appeus/content/locales/eu/LC_MESSAGES/plone.po
appeus/content/profiles/default/catalog.xml
appeus/content/profiles/default/diff_tool.xml
appeus/content/profiles/default/metadata.xml
appeus/content/profiles/default/rolemap.xml
appeus/content/profiles/default/types.xml
appeus/content/profiles/default/types/App.xml
appeus/content/templates/README.txt
appeus/content/templates/appview.pt
appeus/content/templates/facetedpreviewitemapp.pt
docs/HISTORY.txt
docs/INSTALL.txt
docs/LICENSE.GPL
docs/LICENSE.txt