Metadata-Version: 1.1
Name: appeus.content
Version: 1.0
Summary: APP.EUS content-types
Home-page: https://bitbucket.org/codesyntax/appeus.theme/
Author: Mikel Larreategi
Author-email: mlarreategi@codesyntax.com
License: GPL
Platform: UNKNOWN
Classifier: Framework :: Plone
Classifier: Programming Language :: Python
Classifier: Topic :: Software Development :: Libraries :: Python Modules
